{"CONFIGURATION": {
    "MAX_TIME": "0",
    "CONFIG_TYPE": "de.emaeuer.evaluation.EvaluationConfiguration",
    "GENERALIZATION_CAPABILITY": "0.5",
    "ENVIRONMENT_CONFIGURATION": {
        "MAX_STEP_NUMBER": "100000.0",
        "CONFIG_TYPE": "de.emaeuer.environment.configuration.EnvironmentConfiguration",
        "SEED": "9369319",
        "ENVIRONMENT_IMPLEMENTATION_NAME": "PONG",
        "ENVIRONMENT_IMPLEMENTATION": {
            "PADDLE_HEIGHT": "150",
            "PADDLE_VELOCITY": "5",
            "BALL_ANGLE": "200",
            "CONFIG_TYPE": "de.emaeuer.environment.pong.configuration.PongConfiguration",
            "BALL_RADIUS": "20",
            "BALL_VELOCITY": "5",
            "BALL_MAX_REFLECTION_ANGLE": "45"
        },
        "GENERALIZATION_MAX_STEP_NUMBER": "10000.0",
        "TEST_GENERALIZATION": "false",
        "GENERALIZATION_MAX_FITNESS_SCORE": "10000.0"
    },
    "SEED": "9369319",
    "MAX_FITNESS_SCORE": "100.0",
    "TEST_GENERALIZATION": "false",
    "OPTIMIZATION_CONFIGURATION": {
        "PROGRESSION_ITERATIONS": "200",
        "CONFIG_TYPE": "de.emaeuer.optimization.configuration.OptimizationConfiguration",
        "SEED": "9369319",
        "MAX_FITNESS_SCORE": "100.0",
        "NUMBER_OF_RUNS": "10",
        "IMPLEMENTATION_CONFIGURATION": {
            "TOPOLOGY_PHEROMONE": "0.6801(n/k)^0.5201+0.2987",
            "REUSE_SPLIT_KNOWLEDGE": "false",
            "ANTS_PER_ITERATION": "9",
            "DEVIATION_FUNCTION": "(1.1559s)/(k - 1)+0.6837z",
            "UPDATE_STRATEGY": "AGE",
            "SPLIT_PROBABILITY": "max((c^0.8834*t^0.4629)/(0.738d+1), 0)",
            "SOLUTION_WEIGHT_FACTOR": "0.2112",
            "ENABLE_NEURON_ISOLATION": "false",
            "CONNECTION_PHEROMONE": "0.5708(n/k)^0.9503+0.163",
            "CONFIG_TYPE": "de.emaeuer.optimization.dannaco.configuration.DannacoConfiguration",
            "TOPOLOGY_SIMILARITY_THRESHOLD": "0.7",
            "ELITISM": "true",
            "UPDATES_PER_ITERATION": "1",
            "NUMBER_OF_VALUES_PENALTY": "(k-n)/(n+1)",
            "POPULATION_SIZE": "11"
        },
        "METHOD_NAME": "DANN_ACO",
        "PROGRESSION_THRESHOLD": "0.0",
        "GENERALIZATION_CAPABILITY_THRESHOLD": "0.5",
        "TEST_GENERALIZATION": "false",
        "NEURAL_NETWORK_CONFIGURATION": {
            "OUTPUT_ACTIVATION_FUNCTION": "TANH",
            "CONFIG_TYPE": "de.emaeuer.ann.configuration.NeuralNetworkConfiguration",
            "OUTPUT_LAYER_SIZE": "1",
            "INPUT_ACTIVATION_FUNCTION": "IDENTITY",
            "INPUT_LAYER_SIZE": "3",
            "WEIGHT_MIN": "-10.0",
            "WEIGHT_MAX": "10.0",
            "HIDDEN_ACTIVATION_FUNCTION": "TANH",
            "DISABLE_RECURRENT_CONNECTIONS": "false"
        },
        "MAX_NUMBER_OF_EVALUATIONS": "20000"
    },
    "GENERALIZATION_MAX_FITNESS_SCORE": "10000.0"
}}